catenae/__init__.py
catenae/catenae.py
catenae/errors.py
catenae/health.py
catenae/logger.py
catenae/queue.py
catenae/threading.py
catenae/utils.py
catenae_stopover-3.2308.3.dist-info/METADATA
catenae_stopover-3.2308.3.dist-info/WHEEL
catenae_stopover-3.2308.3.dist-info/top_level.txt
catenae_stopover-3.2308.3.dist-info/RECORD
