Metadata-Version: 2.1
Name: catenae-stopover
Version: 3.2308.3
Summary: Catenae 3 – Microservices Framework for Stopover
Home-page: https://github.com/catenae
Author: Rodrigo Martínez
Author-email: dev@brunneis.com
License: GNU General Public License v3.0
Classifier: Development Status :: 4 - Beta
Classifier: Environment :: Console
Classifier: Intended Audience :: Developers
Classifier: License :: OSI Approved :: GNU General Public License v3 (GPLv3)
Classifier: Operating System :: POSIX :: Linux
Classifier: Programming Language :: Python :: 3.6
Classifier: Programming Language :: Python :: Implementation :: PyPy
Classifier: Topic :: Software Development :: Libraries :: Python Modules
Requires-Dist: stopover (<2.0.0,>=1.214.0)
Requires-Dist: falcon (<4.0.0,>=3.0.0)
Requires-Dist: binnakle (<2.0.0,>=1.2212.1)
